{
  "type": "FeatureCollection",
  "features": [
    {"type":"Feature","properties":{"name":"日本橋","id":0},"geometry":{"type":"Point","coordinates":[139.774,35.6824]}},
    {"type":"Feature","properties":{"name":"品川","id":1},"geometry":{"type":"Point","coordinates":[139.739,35.6285]}},
    {"type":"Feature","properties":{"name":"川崎","id":2},"geometry":{"type":"Point","coordinates":[139.703,35.5308]}},
    {"type":"Feature","properties":{"name":"横浜","id":3},"geometry":{"type":"Point","coordinates":[139.638,35.4437]}},
    {"type":"Feature","properties":{"name":"小田原（箱根口）","id":4},"geometry":{"type":"Point","coordinates":[139.155,35.255]}},
    {"type":"Feature","properties":{"name":"沼津","id":5},"geometry":{"type":"Point","coordinates":[138.864,35.095]}},
    {"type":"Feature","properties":{"name":"静岡","id":6},"geometry":{"type":"Point","coordinates":[138.3828,34.9756]}},
    {"type":"Feature","properties":{"name":"浜松","id":7},"geometry":{"type":"Point","coordinates":[137.7261,34.7104]}},
    {"type":"Feature","properties":{"name":"名古屋","id":8},"geometry":{"type":"Point","coordinates":[136.9066,35.1815]}},
    {"type":"Feature","properties":{"name":"京都","id":9},"geometry":{"type":"Point","coordinates":[135.7681,35.0116]}}
  ]
}